[{"label": "person", "confidence": 0.11, "topleft": {"x": 981, "y": 39}, "bottomright": {"x": 1015, "y": 94}}, {"label": "person", "confidence": 0.22, "topleft": {"x": 1063, "y": 48}, "bottomright": {"x": 1117, "y": 132}}, {"label": "person", "confidence": 0.11, "topleft": {"x": 493, "y": 108}, "bottomright": {"x": 525, "y": 154}}, {"label": "person", "confidence": 0.11, "topleft": {"x": 287, "y": 151}, "bottomright": {"x": 319, "y": 188}}, {"label": "person", "confidence": 0.11, "topleft": {"x": 276, "y": 135}, "bottomright": {"x": 326, "y": 217}}, {"label": "person", "confidence": 0.1, "topleft": {"x": 347, "y": 152}, "bottomright": {"x": 382, "y": 190}}, {"label": "person", "confidence": 0.36, "topleft": {"x": 632, "y": 120}, "bottomright": {"x": 679, "y": 239}}, {"label": "person", "confidence": 0.59, "topleft": {"x": 681, "y": 100}, "bottomright": {"x": 729, "y": 264}}, {"label": "person", "confidence": 0.61, "topleft": {"x": 222, "y": 145}, "bottomright": {"x": 287, "y": 278}}, {"label": "person", "confidence": 0.34, "topleft": {"x": 268, "y": 153}, "bottomright": {"x": 315, "y": 265}}, {"label": "person", "confidence": 0.22, "topleft": {"x": 344, "y": 162}, "bottomright": {"x": 395, "y": 251}}, {"label": "person", "confidence": 0.39, "topleft": {"x": 407, "y": 157}, "bottomright": {"x": 457, "y": 257}}, {"label": "person", "confidence": 0.31, "topleft": {"x": 483, "y": 145}, "bottomright": {"x": 528, "y": 252}}, {"label": "person", "confidence": 0.23, "topleft": {"x": 551, "y": 140}, "bottomright": {"x": 599, "y": 262}}, {"label": "person", "confidence": 0.47, "topleft": {"x": 752, "y": 135}, "bottomright": {"x": 811, "y": 291}}, {"label": "person", "confidence": 0.27, "topleft": {"x": 793, "y": 148}, "bottomright": {"x": 849, "y": 282}}, {"label": "person", "confidence": 0.17, "topleft": {"x": 882, "y": 164}, "bottomright": {"x": 943, "y": 259}}, {"label": "person", "confidence": 0.2, "topleft": {"x": 959, "y": 185}, "bottomright": {"x": 994, "y": 236}}, {"label": "person", "confidence": 0.19, "topleft": {"x": 942, "y": 169}, "bottomright": {"x": 1005, "y": 248}}, {"label": "person", "confidence": 0.11, "topleft": {"x": 1023, "y": 181}, "bottomright": {"x": 1057, "y": 226}}, {"label": "person", "confidence": 0.39, "topleft": {"x": 993, "y": 165}, "bottomright": {"x": 1055, "y": 242}}, {"label": "person", "confidence": 0.11, "topleft": {"x": 1241, "y": 182}, "bottomright": {"x": 1267, "y": 233}}, {"label": "person", "confidence": 0.12, "topleft": {"x": 1201, "y": 171}, "bottomright": {"x": 1262, "y": 249}}, {"label": "person", "confidence": 0.68, "topleft": {"x": 118, "y": 157}, "bottomright": {"x": 171, "y": 318}}, {"label": "person", "confidence": 0.59, "topleft": {"x": 588, "y": 124}, "bottomright": {"x": 660, "y": 360}}, {"label": "person", "confidence": 0.69, "topleft": {"x": 210, "y": 34}, "bottomright": {"x": 1069, "y": 449}}, {"label": "person", "confidence": 0.17, "topleft": {"x": 877, "y": 208}, "bottomright": {"x": 940, "y": 290}}, {"label": "person", "confidence": 0.12, "topleft": {"x": 942, "y": 207}, "bottomright": {"x": 1000, "y": 288}}, {"label": "person", "confidence": 0.14, "topleft": {"x": 1029, "y": 223}, "bottomright": {"x": 1057, "y": 268}}, {"label": "person", "confidence": 0.13, "topleft": {"x": 1016, "y": 208}, "bottomright": {"x": 1068, "y": 291}}, {"label": "person", "confidence": 0.13, "topleft": {"x": 1212, "y": 198}, "bottomright": {"x": 1269, "y": 294}}, {"label": "person", "confidence": 0.11, "topleft": {"x": 410, "y": 256}, "bottomright": {"x": 431, "y": 311}}, {"label": "person", "confidence": 0.19, "topleft": {"x": 881, "y": 247}, "bottomright": {"x": 958, "y": 308}}, {"label": "person", "confidence": 0.33, "topleft": {"x": 1010, "y": 233}, "bottomright": {"x": 1065, "y": 334}}, {"label": "person", "confidence": 0.34, "topleft": {"x": 1146, "y": 242}, "bottomright": {"x": 1226, "y": 328}}, {"label": "person", "confidence": 0.15, "topleft": {"x": 1200, "y": 239}, "bottomright": {"x": 1268, "y": 331}}, {"label": "person", "confidence": 0.56, "topleft": {"x": 23, "y": 247}, "bottomright": {"x": 98, "y": 371}}, {"label": "person", "confidence": 0.31, "topleft": {"x": 396, "y": 265}, "bottomright": {"x": 440, "y": 378}}, {"label": "person", "confidence": 0.15, "topleft": {"x": 993, "y": 269}, "bottomright": {"x": 1057, "y": 355}}, {"label": "person", "confidence": 0.64, "topleft": {"x": 313, "y": 277}, "bottomright": {"x": 389, "y": 430}}, {"label": "person", "confidence": 0.39, "topleft": {"x": 393, "y": 291}, "bottomright": {"x": 461, "y": 442}}, {"label": "person", "confidence": 0.24, "topleft": {"x": 378, "y": 267}, "bottomright": {"x": 509, "y": 465}}, {"label": "person", "confidence": 0.78, "topleft": {"x": 452, "y": 290}, "bottomright": {"x": 516, "y": 459}}, {"label": "person", "confidence": 0.68, "topleft": {"x": 657, "y": 318}, "bottomright": {"x": 724, "y": 488}}, {"label": "person", "confidence": 0.25, "topleft": {"x": 334, "y": 185}, "bottomright": {"x": 1199, "y": 677}}, {"label": "person", "confidence": 0.5, "topleft": {"x": 1194, "y": 378}, "bottomright": {"x": 1275, "y": 492}}, {"label": "person", "confidence": 0.75, "topleft": {"x": 851, "y": 355}, "bottomright": {"x": 945, "y": 575}}, {"label": "person", "confidence": 0.53, "topleft": {"x": 980, "y": 465}, "bottomright": {"x": 1049, "y": 580}}, {"label": "person", "confidence": 0.41, "topleft": {"x": 960, "y": 452}, "bottomright": {"x": 1087, "y": 638}}, {"label": "person", "confidence": 0.67, "topleft": {"x": 651, "y": 515}, "bottomright": {"x": 718, "y": 657}}, {"label": "backpack", "confidence": 0.13, "topleft": {"x": 39, "y": 259}, "bottomright": {"x": 74, "y": 313}}, {"label": "sports ball", "confidence": 0.17, "topleft": {"x": 908, "y": 528}, "bottomright": {"x": 927, "y": 552}}, {"label": "tennis racket", "confidence": 0.11, "topleft": {"x": 309, "y": 0}, "bottomright": {"x": 413, "y": 109}}, {"label": "tennis racket", "confidence": 0.13, "topleft": {"x": 413, "y": 290}, "bottomright": {"x": 438, "y": 352}}, {"label": "chair", "confidence": 0.14, "topleft": {"x": 347, "y": 192}, "bottomright": {"x": 382, "y": 227}}, {"label": "chair", "confidence": 0.1, "topleft": {"x": 355, "y": 224}, "bottomright": {"x": 385, "y": 246}}]